findanywhere/__init__.py
findanywhere/adapters/__init__.py
findanywhere/adapters/evaluation/__init__.py
findanywhere/adapters/evaluation/string_distance.py
findanywhere/adapters/source/__init__.py
findanywhere/adapters/source/jsonlike.py
findanywhere/adapters/source/tabular.py
findanywhere/adapters/source/text.py
findanywhere/adapters/source/website.py
findanywhere/adapters/source/xmllike.py
findanywhere/algorithms/__init__.py
findanywhere/algorithms/jsonlike.py
findanywhere/algorithms/strings.py
findanywhere/ports/__init__.py
findanywhere/ports/evaluation.py
findanywhere/ports/source.py
findanywhere/schema.py
findanywhere/scores/__init__.py
findanywhere/scores/deduction.py
findanywhere/search/__init__.py
findanywhere/search/base.py
findanywhere/search/parallel.py
findanywhere/search/sequential.py
findanywhere/similarity/__init__.py
findanywhere/similarity/common.py
findanywhere/similarity/rest.py
findanywhere/similarity/token.py
findanywhere/thresholds/__init__.py
findanywhere/thresholds/basic.py
findanywhere/tokeinize/__init__.py
findanywhere/tokeinize/common.py
findanywhere/types/__init__.py
findanywhere/types/common.py
findanywhere/types/entry.py
findanywhere/types/factory.py
findanywhere/types/input_data.py
findanywhere/types/similarity.py
findanywhere/types/tokenize.py
findanywhere/ui/__init__.py
findanywhere/ui/console.py
findanywhere/utils/__init__.py
findanywhere/utils/buffer_database.py
findanywhere-1.6.5.dist-info/LICENSE
findanywhere-1.6.5.dist-info/METADATA
findanywhere-1.6.5.dist-info/WHEEL
findanywhere-1.6.5.dist-info/entry_points.txt
findanywhere-1.6.5.dist-info/RECORD
