Metadata-Version: 2.3
Name: findanywhere
Version: 1.6.5
Summary: Tool for searching data in possible malformed input data as preprocessing step for further analysis.
License: BSD License (BSD)
Keywords: search,fuzzy_search,preprocessing
Author: voidpointercast
Author-email: voidpointercast@justmail.de
Requires-Python: >=3.10,<4.0
Classifier: Development Status :: 4 - Beta
Classifier: Environment :: Console
Classifier: Intended Audience :: Science/Research
Classifier: License :: OSI Approved :: BSD License
Classifier: License :: Other/Proprietary License
Classifier: Operating System :: Microsoft :: Windows :: Windows 11
Classifier: Operating System :: POSIX :: Linux
Classifier: Programming Language :: Python :: 3
Classifier: Programming Language :: Python :: 3.10
Classifier: Programming Language :: Python :: 3.11
Classifier: Programming Language :: Python :: 3.12
Classifier: Programming Language :: Python :: 3.13
Classifier: Topic :: Scientific/Engineering :: Information Analysis
Requires-Dist: beautifulsoup4 (>=4.12.3,<5.0.0)
Requires-Dist: dacite (>=1.8.1,<2.0.0)
Requires-Dist: jellyfish (>=1.0.3,<2.0.0)
Requires-Dist: pyyaml (>=6.0.1,<7.0.0)
Requires-Dist: requests (>=2.32.3,<3.0.0)
Requires-Dist: sqlalchemy (>=2.0.31,<3.0.0)
Requires-Dist: toolz (>=1.0.0,<2.0.0)
Project-URL: Documentation, https://findanywhere.readthedocs.io/en/latest
Project-URL: Homepage, https://gitlab.com/patrick.daniel.gress/findanywhere
Project-URL: Repository, https://gitlab.com/patrick.daniel.gress/findanywhere
